docp_docling/__init__.py
docp_docling/libs/_version.py
docp_docling/libs/changelog.py
docp_docling/libs/startup.py
docp_docling/parsers/pdfparser.py
docp_docling-1.0.1.dist-info/licenses/LICENSE
docp_docling-1.0.1.dist-info/METADATA
docp_docling-1.0.1.dist-info/WHEEL
docp_docling-1.0.1.dist-info/top_level.txt
docp_docling-1.0.1.dist-info/RECORD
